<?xml version="1.0" encoding="utf-8" standalone="yes"?>
<Scene_Memory_DesertDragon_Level6>
  <EntryTask F_heartrate="0.3" I_compres="0" V_eventpos="0:0:0" I_typeid="0" I_monsternum="0" B_killall="0" B_IsInitialized="0" I_eventskillid="0" I_HashRes="0" F_random="0" I_num="0" I_num1="0">
    <Selector>
      <Sequence>
        <ReceiveAIEvent Deprecate="0" MsgType="1" Shared_MsgStrName="eventcmd" Shared_TypeIdName="typeid" Shared_TypeIdmValue="0" Shared_PosName="eventpos" Shared_PosmValue="0:0:0" Shared_SkillTemplateIdName="" Shared_SkillTemplateIdmValue="0" Shared_SkillIdName="eventskillid" Shared_SkillIdmValue="0" Shared_FloatArgName="" Shared_FloatArgmValue="0" Shared_SenderUIDName="" />
        <CompareTo Shared_FirstStringName="eventcmd" Shared_SecondStringName="" secondString="flywind" Shared_ResultName="compres" />
        <IntComparison type="2" Shared_Int1Name="compres" int1Value="0" Shared_Int2Name="" int2Value="0" />
        <CallMonster Shared_DistName="" Shared_DistmValue="0" Shared_AngleName="" Shared_AnglemValue="0" MonsterId="43261" Shared_MonsterId2Name="" Shared_MonsterId2mValue="0" CopyMonsterId="0" MaxMonsterNum="1" LifeTime="8" DelayTime="1" Shared_PosName="eventpos" Shared_PosmValue="0:0:0" BornType="1" Pos1="76.85:9:69" Pos2="76.85:9:69" Pos3="76.85:9:69" Pos4="76.85:9:69" FinalPos="76.85:9:69" ForcePlace="0" DeltaArg="0" HPPercent="0" />
        <RandomEntityPos TemplateId="43261" Radius="1" CenterPos="0:0:0" FinalPos="76.85:9:69" NearPlayerTemplateId="-1" />
      </Sequence>
      <Sequence>
        <ReceiveAIEvent Deprecate="0" MsgType="1" Shared_MsgStrName="eventcmd" Shared_TypeIdName="typeid" Shared_TypeIdmValue="0" Shared_PosName="eventpos" Shared_PosmValue="0:0:0" Shared_SkillTemplateIdName="" Shared_SkillTemplateIdmValue="0" Shared_SkillIdName="eventskillid" Shared_SkillIdmValue="0" Shared_FloatArgName="" Shared_FloatArgmValue="0" Shared_SenderUIDName="" />
        <CompareTo Shared_FirstStringName="eventcmd" Shared_SecondStringName="" secondString="followboom" Shared_ResultName="compres" />
        <IntComparison type="2" Shared_Int1Name="compres" int1Value="0" Shared_Int2Name="" int2Value="0" />
        <RandomFloat Shared_MinName="" minValue="0" Shared_MaxName="" maxValue="2" inclusive="0" Shared_StoredResultName="random" />
        <Selector>
          <Sequence>
            <FloatComparison type="1" Shared_Float1Name="random" float1Value="0" Shared_Float2Name="" float2Value="1" />
            <CallMonster Shared_DistName="" Shared_DistmValue="0" Shared_AngleName="" Shared_AnglemValue="0" MonsterId="43264" Shared_MonsterId2Name="" Shared_MonsterId2mValue="0" CopyMonsterId="0" MaxMonsterNum="1" LifeTime="6" DelayTime="2" Shared_PosName="eventpos" Shared_PosmValue="0:0:0" BornType="1" Pos1="76.85:9:69" Pos2="76.85:9:69" Pos3="76.85:9:69" Pos4="76.85:9:69" FinalPos="76.85:9:69" ForcePlace="0" DeltaArg="0" HPPercent="0" />
          </Sequence>
          <Sequence>
            <FloatComparison type="1" Shared_Float1Name="random" float1Value="0" Shared_Float2Name="" float2Value="2" />
            <CallMonster Shared_DistName="" Shared_DistmValue="0" Shared_AngleName="" Shared_AnglemValue="0" MonsterId="43265" Shared_MonsterId2Name="" Shared_MonsterId2mValue="0" CopyMonsterId="0" MaxMonsterNum="1" LifeTime="6" DelayTime="2" Shared_PosName="eventpos" Shared_PosmValue="0:0:0" BornType="1" Pos1="76.85:9:69" Pos2="76.85:9:69" Pos3="76.85:9:69" Pos4="76.85:9:69" FinalPos="76.85:9:69" ForcePlace="0" DeltaArg="0" HPPercent="0" />
          </Sequence>
        </Selector>
        <AddBuff Shared_MonsterIdName="" Shared_MonsterIdmValue="0" Shared_BuffIdName="" Shared_BuffIdmValue="121430" Shared_BuffId2Name="" Shared_BuffId2mValue="0" Shared_AddBuffTargetName="" Shared_AddBuffTargetmValue="1" Shared_AddBuffWayName="" Shared_AddBuffWaymValue="0" Shared_PlayerProfIdName="" Shared_PlayerProfIdmValue="0" />
      </Sequence>
      <Sequence>
        <ReceiveAIEvent Deprecate="0" MsgType="1" Shared_MsgStrName="eventcmd" Shared_TypeIdName="typeid" Shared_TypeIdmValue="0" Shared_PosName="eventpos" Shared_PosmValue="0:0:0" Shared_SkillTemplateIdName="" Shared_SkillTemplateIdmValue="0" Shared_SkillIdName="eventskillid" Shared_SkillIdmValue="0" Shared_FloatArgName="" Shared_FloatArgmValue="0" Shared_SenderUIDName="" />
        <CompareTo Shared_FirstStringName="eventcmd" Shared_SecondStringName="" secondString="flyattack" Shared_ResultName="compres" />
        <IntComparison type="2" Shared_Int1Name="compres" int1Value="0" Shared_Int2Name="" int2Value="0" />
        <RandomFloat Shared_MinName="" minValue="0" Shared_MaxName="" maxValue="2" inclusive="0" Shared_StoredResultName="random" />
        <Selector>
          <Sequence>
            <FloatComparison type="1" Shared_Float1Name="random" float1Value="0" Shared_Float2Name="" float2Value="1" />
            <CallMonster Shared_DistName="" Shared_DistmValue="0" Shared_AngleName="" Shared_AnglemValue="0" MonsterId="43262" Shared_MonsterId2Name="" Shared_MonsterId2mValue="0" CopyMonsterId="0" MaxMonsterNum="1" LifeTime="11" DelayTime="2" Shared_PosName="eventpos" Shared_PosmValue="0:0:0" BornType="1" Pos1="76.85:9:69" Pos2="76.85:9:69" Pos3="76.85:9:69" Pos4="76.85:9:69" FinalPos="76.85:9:69" ForcePlace="0" DeltaArg="0" HPPercent="0" />
          </Sequence>
          <Sequence>
            <FloatComparison type="1" Shared_Float1Name="random" float1Value="0" Shared_Float2Name="" float2Value="2" />
            <CallMonster Shared_DistName="" Shared_DistmValue="0" Shared_AngleName="" Shared_AnglemValue="0" MonsterId="43263" Shared_MonsterId2Name="" Shared_MonsterId2mValue="0" CopyMonsterId="0" MaxMonsterNum="1" LifeTime="11" DelayTime="2" Shared_PosName="eventpos" Shared_PosmValue="0:0:0" BornType="1" Pos1="76.85:9:69" Pos2="76.85:9:69" Pos3="76.85:9:69" Pos4="76.85:9:69" FinalPos="76.85:9:69" ForcePlace="0" DeltaArg="0" HPPercent="0" />
          </Sequence>
        </Selector>
        <CallScript FuncName="noticeflyattack" DelayTime="0" />
        <AddBuff Shared_MonsterIdName="" Shared_MonsterIdmValue="0" Shared_BuffIdName="" Shared_BuffIdmValue="121429" Shared_BuffId2Name="" Shared_BuffId2mValue="0" Shared_AddBuffTargetName="" Shared_AddBuffTargetmValue="1" Shared_AddBuffWayName="" Shared_AddBuffWaymValue="0" Shared_PlayerProfIdName="" Shared_PlayerProfIdmValue="0" />
      </Sequence>
      <Sequence>
        <ReceiveAIEvent Deprecate="0" MsgType="1" Shared_MsgStrName="eventcmd" Shared_TypeIdName="typeid" Shared_TypeIdmValue="0" Shared_PosName="eventpos" Shared_PosmValue="0:0:0" Shared_SkillTemplateIdName="" Shared_SkillTemplateIdmValue="0" Shared_SkillIdName="eventskillid" Shared_SkillIdmValue="0" Shared_FloatArgName="" Shared_FloatArgmValue="0" Shared_SenderUIDName="" />
        <CompareTo Shared_FirstStringName="eventcmd" Shared_SecondStringName="" secondString="downground" Shared_ResultName="compres" />
        <IntComparison type="2" Shared_Int1Name="compres" int1Value="0" Shared_Int2Name="" int2Value="0" />
        <RandomFloat Shared_MinName="" minValue="0" Shared_MaxName="" maxValue="2" inclusive="0" Shared_StoredResultName="random" />
        <Selector>
          <Sequence>
            <FloatComparison type="1" Shared_Float1Name="random" float1Value="0" Shared_Float2Name="" float2Value="1" />
            <CallMonster Shared_DistName="" Shared_DistmValue="0" Shared_AngleName="" Shared_AnglemValue="0" MonsterId="43270" Shared_MonsterId2Name="" Shared_MonsterId2mValue="0" CopyMonsterId="0" MaxMonsterNum="2" LifeTime="0" DelayTime="6" Shared_PosName="eventpos" Shared_PosmValue="0:0:0" BornType="1" Pos1="76.85:9:69" Pos2="76.85:9:69" Pos3="76.85:9:69" Pos4="76.85:9:69" FinalPos="76.85:9:69" ForcePlace="0" DeltaArg="0" HPPercent="0" />
            <CallMonster Shared_DistName="" Shared_DistmValue="0" Shared_AngleName="" Shared_AnglemValue="0" MonsterId="43271" Shared_MonsterId2Name="" Shared_MonsterId2mValue="0" CopyMonsterId="0" MaxMonsterNum="2" LifeTime="0" DelayTime="6" Shared_PosName="eventpos" Shared_PosmValue="0:0:0" BornType="1" Pos1="54.38:9:68.59" Pos2="54.38:9:68.59" Pos3="54.38:9:68.59" Pos4="54.38:9:68.59" FinalPos="54.38:9:68.59" ForcePlace="0" DeltaArg="0" HPPercent="0" />
          </Sequence>
          <Sequence>
            <FloatComparison type="1" Shared_Float1Name="random" float1Value="0" Shared_Float2Name="" float2Value="2" />
            <CallMonster Shared_DistName="" Shared_DistmValue="0" Shared_AngleName="" Shared_AnglemValue="0" MonsterId="43271" Shared_MonsterId2Name="" Shared_MonsterId2mValue="0" CopyMonsterId="0" MaxMonsterNum="2" LifeTime="0" DelayTime="6" Shared_PosName="eventpos" Shared_PosmValue="0:0:0" BornType="1" Pos1="76.85:9:69" Pos2="76.85:9:69" Pos3="76.85:9:69" Pos4="76.85:9:69" FinalPos="76.85:9:69" ForcePlace="0" DeltaArg="0" HPPercent="0" />
            <CallMonster Shared_DistName="" Shared_DistmValue="0" Shared_AngleName="" Shared_AnglemValue="0" MonsterId="43270" Shared_MonsterId2Name="" Shared_MonsterId2mValue="0" CopyMonsterId="0" MaxMonsterNum="2" LifeTime="0" DelayTime="6" Shared_PosName="eventpos" Shared_PosmValue="0:0:0" BornType="1" Pos1="54.38:9:68.59" Pos2="54.38:9:68.59" Pos3="54.38:9:68.59" Pos4="54.38:9:68.59" FinalPos="54.38:9:68.59" ForcePlace="0" DeltaArg="0" HPPercent="0" />
          </Sequence>
        </Selector>
        <CallScript FuncName="noticedownground" DelayTime="5" />
        <CallScript FuncName="noticedownground1" DelayTime="12" />
      </Sequence>
      <Sequence>
        <ReceiveAIEvent Deprecate="0" MsgType="1" Shared_MsgStrName="eventcmd" Shared_TypeIdName="typeid" Shared_TypeIdmValue="0" Shared_PosName="eventpos" Shared_PosmValue="0:0:0" Shared_SkillTemplateIdName="" Shared_SkillTemplateIdmValue="0" Shared_SkillIdName="" Shared_SkillIdmValue="0" Shared_FloatArgName="" Shared_FloatArgmValue="0" Shared_SenderUIDName="" />
        <CompareTo Shared_FirstStringName="eventcmd" Shared_SecondStringName="" secondString="Dead" Shared_ResultName="compres" />
        <IntComparison type="2" Shared_Int1Name="compres" int1Value="0" Shared_Int2Name="" int2Value="0" />
        <IntComparison type="2" Shared_Int1Name="typeid" int1Value="0" Shared_Int2Name="" int2Value="43270" />
        <CallMonster Shared_DistName="" Shared_DistmValue="0" Shared_AngleName="" Shared_AnglemValue="0" MonsterId="43273" Shared_MonsterId2Name="" Shared_MonsterId2mValue="0" CopyMonsterId="0" MaxMonsterNum="1" LifeTime="12" DelayTime="0" Shared_PosName="eventpos" Shared_PosmValue="0:0:0" BornType="2" Pos1="0:0:0" Pos2="0:0:0" Pos3="0:0:0" Pos4="0:0:0" FinalPos="0:0:0" ForcePlace="0" DeltaArg="0" HPPercent="0" />
      </Sequence>
      <Sequence>
        <ReceiveAIEvent Deprecate="0" MsgType="1" Shared_MsgStrName="eventcmd" Shared_TypeIdName="typeid" Shared_TypeIdmValue="0" Shared_PosName="eventpos" Shared_PosmValue="0:0:0" Shared_SkillTemplateIdName="" Shared_SkillTemplateIdmValue="0" Shared_SkillIdName="eventskillid" Shared_SkillIdmValue="0" Shared_FloatArgName="" Shared_FloatArgmValue="0" Shared_SenderUIDName="" />
        <CompareTo Shared_FirstStringName="eventcmd" Shared_SecondStringName="" secondString="lifeeyes" Shared_ResultName="compres" />
        <IntComparison type="2" Shared_Int1Name="compres" int1Value="0" Shared_Int2Name="" int2Value="0" />
        <AddBuff Shared_MonsterIdName="" Shared_MonsterIdmValue="0" Shared_BuffIdName="" Shared_BuffIdmValue="121444" Shared_BuffId2Name="" Shared_BuffId2mValue="0" Shared_AddBuffTargetName="" Shared_AddBuffTargetmValue="1" Shared_AddBuffWayName="" Shared_AddBuffWaymValue="0" Shared_PlayerProfIdName="" Shared_PlayerProfIdmValue="0" />
        <CallMonster Shared_DistName="" Shared_DistmValue="0" Shared_AngleName="" Shared_AnglemValue="90" MonsterId="43267" Shared_MonsterId2Name="" Shared_MonsterId2mValue="0" CopyMonsterId="0" MaxMonsterNum="4" LifeTime="9" DelayTime="0" Shared_PosName="eventpos" Shared_PosmValue="0:0:0" BornType="1" Pos1="45:9:68" Pos2="45:9:68" Pos3="45:9:68" Pos4="45:9:68" FinalPos="45:9:68" ForcePlace="0" DeltaArg="0" HPPercent="0" />
        <CallMonster Shared_DistName="" Shared_DistmValue="0" Shared_AngleName="" Shared_AnglemValue="0" MonsterId="43267" Shared_MonsterId2Name="" Shared_MonsterId2mValue="0" CopyMonsterId="0" MaxMonsterNum="4" LifeTime="9" DelayTime="0" Shared_PosName="eventpos" Shared_PosmValue="0:0:0" BornType="1" Pos1="65.76:9:48.41" Pos2="65.76:9:48.41" Pos3="65.76:9:48.41" Pos4="65.76:9:48.41" FinalPos="65.76:9:48.41" ForcePlace="0" DeltaArg="0" HPPercent="0" />
        <CallMonster Shared_DistName="" Shared_DistmValue="0" Shared_AngleName="" Shared_AnglemValue="-90" MonsterId="43267" Shared_MonsterId2Name="" Shared_MonsterId2mValue="0" CopyMonsterId="0" MaxMonsterNum="4" LifeTime="9" DelayTime="0" Shared_PosName="eventpos" Shared_PosmValue="0:0:0" BornType="1" Pos1="86.26:9:69.28" Pos2="86.26:9:69.28" Pos3="86.26:9:69.28" Pos4="86.26:9:69.28" FinalPos="86.26:9:69.28" ForcePlace="0" DeltaArg="0" HPPercent="0" />
        <CallMonster Shared_DistName="" Shared_DistmValue="0" Shared_AngleName="" Shared_AnglemValue="180" MonsterId="43267" Shared_MonsterId2Name="" Shared_MonsterId2mValue="0" CopyMonsterId="0" MaxMonsterNum="4" LifeTime="9" DelayTime="0" Shared_PosName="eventpos" Shared_PosmValue="0:0:0" BornType="1" Pos1="65.27:9:89.74" Pos2="65.27:9:89.74" Pos3="65.27:9:89.74" Pos4="65.27:9:89.74" FinalPos="65.27:9:89.74" ForcePlace="0" DeltaArg="0" HPPercent="0" />
        <CallScript FuncName="noticelifeeyes" DelayTime="0" />
        <SendAIEvent MsgTo="7" MsgType="1" EntityTypeId="0" MsgStr="resetnum" Shared_PosName="" Shared_PosmValue="0:0:0" DelayTime="8" />
      </Sequence>
      <Sequence>
        <ReceiveAIEvent Deprecate="0" MsgType="1" Shared_MsgStrName="eventcmd" Shared_TypeIdName="typeid" Shared_TypeIdmValue="0" Shared_PosName="eventpos" Shared_PosmValue="0:0:0" Shared_SkillTemplateIdName="" Shared_SkillTemplateIdmValue="0" Shared_SkillIdName="" Shared_SkillIdmValue="0" Shared_FloatArgName="" Shared_FloatArgmValue="0" Shared_SenderUIDName="" />
        <CompareTo Shared_FirstStringName="eventcmd" Shared_SecondStringName="" secondString="Dead" Shared_ResultName="compres" />
        <IntComparison type="2" Shared_Int1Name="compres" int1Value="0" Shared_Int2Name="" int2Value="0" />
        <IntComparison type="2" Shared_Int1Name="typeid" int1Value="0" Shared_Int2Name="" int2Value="43267" />
        <IntOperator type="0" Shared_Int1Name="num" int1Value="0" Shared_Int2Name="" int2Value="1" Shared_StoredResultName="num" />
        <IntComparison type="2" Shared_Int1Name="num" int1Value="0" Shared_Int2Name="" int2Value="4" />
        <AddBuff Shared_MonsterIdName="" Shared_MonsterIdmValue="0" Shared_BuffIdName="" Shared_BuffIdmValue="121431" Shared_BuffId2Name="" Shared_BuffId2mValue="0" Shared_AddBuffTargetName="" Shared_AddBuffTargetmValue="1" Shared_AddBuffWayName="" Shared_AddBuffWaymValue="0" Shared_PlayerProfIdName="" Shared_PlayerProfIdmValue="0" />
      </Sequence>
      <Sequence>
        <ReceiveAIEvent Deprecate="0" MsgType="1" Shared_MsgStrName="eventcmd" Shared_TypeIdName="typeid" Shared_TypeIdmValue="0" Shared_PosName="eventpos" Shared_PosmValue="0:0:0" Shared_SkillTemplateIdName="" Shared_SkillTemplateIdmValue="0" Shared_SkillIdName="" Shared_SkillIdmValue="0" Shared_FloatArgName="" Shared_FloatArgmValue="0" Shared_SenderUIDName="" />
        <CompareTo Shared_FirstStringName="eventcmd" Shared_SecondStringName="" secondString="resetnum" Shared_ResultName="compres" />
        <IntComparison type="2" Shared_Int1Name="compres" int1Value="0" Shared_Int2Name="" int2Value="0" />
        <SetInt Shared_ValueName="" value="0" Shared_StoredResultName="num" />
      </Sequence>
      <Sequence>
        <ReceiveAIEvent Deprecate="0" MsgType="1" Shared_MsgStrName="eventcmd" Shared_TypeIdName="typeid" Shared_TypeIdmValue="0" Shared_PosName="eventpos" Shared_PosmValue="0:0:0" Shared_SkillTemplateIdName="" Shared_SkillTemplateIdmValue="0" Shared_SkillIdName="" Shared_SkillIdmValue="0" Shared_FloatArgName="" Shared_FloatArgmValue="0" Shared_SenderUIDName="" />
        <CompareTo Shared_FirstStringName="eventcmd" Shared_SecondStringName="" secondString="icebind" Shared_ResultName="compres" />
        <IntComparison type="2" Shared_Int1Name="compres" int1Value="0" Shared_Int2Name="" int2Value="0" />
        <AddBuff Shared_MonsterIdName="" Shared_MonsterIdmValue="0" Shared_BuffIdName="" Shared_BuffIdmValue="121442" Shared_BuffId2Name="" Shared_BuffId2mValue="0" Shared_AddBuffTargetName="" Shared_AddBuffTargetmValue="1" Shared_AddBuffWayName="" Shared_AddBuffWaymValue="0" Shared_PlayerProfIdName="" Shared_PlayerProfIdmValue="0" />
        <CallScript FuncName="noticeicebind" DelayTime="0" />
      </Sequence>
      <Sequence>
        <ReceiveAIEvent Deprecate="0" MsgType="1" Shared_MsgStrName="eventcmd" Shared_TypeIdName="typeid" Shared_TypeIdmValue="0" Shared_PosName="eventpos" Shared_PosmValue="0:0:0" Shared_SkillTemplateIdName="" Shared_SkillTemplateIdmValue="0" Shared_SkillIdName="" Shared_SkillIdmValue="0" Shared_FloatArgName="" Shared_FloatArgmValue="0" Shared_SenderUIDName="" />
        <CompareTo Shared_FirstStringName="eventcmd" Shared_SecondStringName="" secondString="poisonworld" Shared_ResultName="compres" />
        <IntComparison type="2" Shared_Int1Name="compres" int1Value="0" Shared_Int2Name="" int2Value="0" />
        <AddBuff Shared_MonsterIdName="" Shared_MonsterIdmValue="0" Shared_BuffIdName="" Shared_BuffIdmValue="121443" Shared_BuffId2Name="" Shared_BuffId2mValue="0" Shared_AddBuffTargetName="" Shared_AddBuffTargetmValue="1" Shared_AddBuffWayName="" Shared_AddBuffWaymValue="0" Shared_PlayerProfIdName="" Shared_PlayerProfIdmValue="0" />
      </Sequence>
      <Sequence>
        <ReceiveAIEvent Deprecate="0" MsgType="1" Shared_MsgStrName="eventcmd" Shared_TypeIdName="typeid" Shared_TypeIdmValue="0" Shared_PosName="eventpos" Shared_PosmValue="0:0:0" Shared_SkillTemplateIdName="" Shared_SkillTemplateIdmValue="0" Shared_SkillIdName="" Shared_SkillIdmValue="0" Shared_FloatArgName="" Shared_FloatArgmValue="0" Shared_SenderUIDName="" />
        <CompareTo Shared_FirstStringName="eventcmd" Shared_SecondStringName="" secondString="Dead" Shared_ResultName="compres" />
        <IntComparison type="2" Shared_Int1Name="compres" int1Value="0" Shared_Int2Name="" int2Value="0" />
        <IntComparison type="2" Shared_Int1Name="typeid" int1Value="0" Shared_Int2Name="" int2Value="43272" />
        <IntOperator type="0" Shared_Int1Name="num1" int1Value="0" Shared_Int2Name="" int2Value="1" Shared_StoredResultName="num1" />
        <IntComparison type="2" Shared_Int1Name="num1" int1Value="0" Shared_Int2Name="" int2Value="4" />
        <AddBuff Shared_MonsterIdName="" Shared_MonsterIdmValue="43201" Shared_BuffIdName="" Shared_BuffIdmValue="121438" Shared_BuffId2Name="" Shared_BuffId2mValue="0" Shared_AddBuffTargetName="" Shared_AddBuffTargetmValue="0" Shared_AddBuffWayName="" Shared_AddBuffWaymValue="0" Shared_PlayerProfIdName="" Shared_PlayerProfIdmValue="0" />
      </Sequence>
      <Sequence>
        <ReceiveAIEvent Deprecate="0" MsgType="1" Shared_MsgStrName="eventcmd" Shared_TypeIdName="typeid" Shared_TypeIdmValue="0" Shared_PosName="eventpos" Shared_PosmValue="0:0:0" Shared_SkillTemplateIdName="" Shared_SkillTemplateIdmValue="0" Shared_SkillIdName="eventskillid" Shared_SkillIdmValue="0" Shared_FloatArgName="" Shared_FloatArgmValue="0" Shared_SenderUIDName="" />
        <CompareTo Shared_FirstStringName="eventcmd" Shared_SecondStringName="" secondString="downbreath" Shared_ResultName="compres" />
        <IntComparison type="2" Shared_Int1Name="compres" int1Value="0" Shared_Int2Name="" int2Value="0" />
        <CallMonster Shared_DistName="" Shared_DistmValue="0" Shared_AngleName="" Shared_AnglemValue="90" MonsterId="43266" Shared_MonsterId2Name="" Shared_MonsterId2mValue="0" CopyMonsterId="0" MaxMonsterNum="1" LifeTime="15" DelayTime="0" Shared_PosName="eventpos" Shared_PosmValue="0:0:0" BornType="1" Pos1="65.9:9:69.2" Pos2="65.9:9:69.2" Pos3="65.9:9:69.2" Pos4="65.9:9:69.2" FinalPos="65.9:9:69.2" ForcePlace="0" DeltaArg="0" HPPercent="0" />
        <RandomFloat Shared_MinName="" minValue="0" Shared_MaxName="" maxValue="2" inclusive="0" Shared_StoredResultName="random" />
        <Selector>
          <Sequence>
            <FloatComparison type="1" Shared_Float1Name="random" float1Value="0" Shared_Float2Name="" float2Value="1" />
            <CallMonster Shared_DistName="" Shared_DistmValue="0" Shared_AngleName="" Shared_AnglemValue="0" MonsterId="43253" Shared_MonsterId2Name="" Shared_MonsterId2mValue="0" CopyMonsterId="0" MaxMonsterNum="1" LifeTime="15" DelayTime="0" Shared_PosName="eventpos" Shared_PosmValue="0:0:0" BornType="1" Pos1="65.9:9:69.2" Pos2="65.9:9:69.2" Pos3="65.9:9:69.2" Pos4="65.9:9:69.2" FinalPos="65.9:9:69.2" ForcePlace="0" DeltaArg="0" HPPercent="0" />
            <CallMonster Shared_DistName="" Shared_DistmValue="0" Shared_AngleName="" Shared_AnglemValue="60" MonsterId="43254" Shared_MonsterId2Name="" Shared_MonsterId2mValue="0" CopyMonsterId="0" MaxMonsterNum="2" LifeTime="15" DelayTime="0" Shared_PosName="eventpos" Shared_PosmValue="0:0:0" BornType="1" Pos1="65.9:9:69.2" Pos2="65.9:9:69.2" Pos3="65.9:9:69.2" Pos4="65.9:9:69.2" FinalPos="65.9:9:69.2" ForcePlace="0" DeltaArg="0" HPPercent="0" />
            <CallMonster Shared_DistName="" Shared_DistmValue="0" Shared_AngleName="" Shared_AnglemValue="120" MonsterId="43255" Shared_MonsterId2Name="" Shared_MonsterId2mValue="0" CopyMonsterId="0" MaxMonsterNum="2" LifeTime="15" DelayTime="0" Shared_PosName="eventpos" Shared_PosmValue="0:0:0" BornType="1" Pos1="65.9:9:69.2" Pos2="65.9:9:69.2" Pos3="65.9:9:69.2" Pos4="65.9:9:69.2" FinalPos="65.9:9:69.2" ForcePlace="0" DeltaArg="0" HPPercent="0" />
            <CallMonster Shared_DistName="" Shared_DistmValue="0" Shared_AngleName="" Shared_AnglemValue="180" MonsterId="43256" Shared_MonsterId2Name="" Shared_MonsterId2mValue="0" CopyMonsterId="0" MaxMonsterNum="1" LifeTime="15" DelayTime="0" Shared_PosName="eventpos" Shared_PosmValue="0:0:0" BornType="1" Pos1="65.9:9:69.2" Pos2="65.9:9:69.2" Pos3="65.9:9:69.2" Pos4="65.9:9:69.2" FinalPos="65.9:9:69.2" ForcePlace="0" DeltaArg="0" HPPercent="0" />
            <CallMonster Shared_DistName="" Shared_DistmValue="0" Shared_AngleName="" Shared_AnglemValue="240" MonsterId="43255" Shared_MonsterId2Name="" Shared_MonsterId2mValue="0" CopyMonsterId="0" MaxMonsterNum="2" LifeTime="15" DelayTime="0" Shared_PosName="eventpos" Shared_PosmValue="0:0:0" BornType="1" Pos1="65.9:9:69.2" Pos2="65.9:9:69.2" Pos3="65.9:9:69.2" Pos4="65.9:9:69.2" FinalPos="65.9:9:69.2" ForcePlace="0" DeltaArg="0" HPPercent="0" />
            <CallMonster Shared_DistName="" Shared_DistmValue="0" Shared_AngleName="" Shared_AnglemValue="300" MonsterId="43254" Shared_MonsterId2Name="" Shared_MonsterId2mValue="0" CopyMonsterId="0" MaxMonsterNum="2" LifeTime="15" DelayTime="0" Shared_PosName="eventpos" Shared_PosmValue="0:0:0" BornType="1" Pos1="65.9:9:69.2" Pos2="65.9:9:69.2" Pos3="65.9:9:69.2" Pos4="65.9:9:69.2" FinalPos="65.9:9:69.2" ForcePlace="0" DeltaArg="0" HPPercent="0" />
          </Sequence>
          <Sequence>
            <FloatComparison type="1" Shared_Float1Name="random" float1Value="0" Shared_Float2Name="" float2Value="2" />
            <CallMonster Shared_DistName="" Shared_DistmValue="0" Shared_AngleName="" Shared_AnglemValue="0" MonsterId="43257" Shared_MonsterId2Name="" Shared_MonsterId2mValue="0" CopyMonsterId="0" MaxMonsterNum="4" LifeTime="15" DelayTime="0" Shared_PosName="eventpos" Shared_PosmValue="0:0:0" BornType="1" Pos1="65.9:9:69.2" Pos2="65.9:9:69.2" Pos3="65.9:9:69.2" Pos4="65.9:9:69.2" FinalPos="65.9:9:69.2" ForcePlace="0" DeltaArg="0" HPPercent="0" />
            <CallMonster Shared_DistName="" Shared_DistmValue="0" Shared_AngleName="" Shared_AnglemValue="90" MonsterId="43257" Shared_MonsterId2Name="" Shared_MonsterId2mValue="0" CopyMonsterId="0" MaxMonsterNum="4" LifeTime="15" DelayTime="0" Shared_PosName="eventpos" Shared_PosmValue="0:0:0" BornType="1" Pos1="65.9:9:69.2" Pos2="65.9:9:69.2" Pos3="65.9:9:69.2" Pos4="65.9:9:69.2" FinalPos="65.9:9:69.2" ForcePlace="0" DeltaArg="0" HPPercent="0" />
            <CallMonster Shared_DistName="" Shared_DistmValue="0" Shared_AngleName="" Shared_AnglemValue="45" MonsterId="43258" Shared_MonsterId2Name="" Shared_MonsterId2mValue="0" CopyMonsterId="0" MaxMonsterNum="4" LifeTime="15" DelayTime="0" Shared_PosName="eventpos" Shared_PosmValue="0:0:0" BornType="1" Pos1="65.9:9:69.2" Pos2="65.9:9:69.2" Pos3="65.9:9:69.2" Pos4="65.9:9:69.2" FinalPos="65.9:9:69.2" ForcePlace="0" DeltaArg="0" HPPercent="0" />
            <CallMonster Shared_DistName="" Shared_DistmValue="0" Shared_AngleName="" Shared_AnglemValue="180" MonsterId="43257" Shared_MonsterId2Name="" Shared_MonsterId2mValue="0" CopyMonsterId="0" MaxMonsterNum="4" LifeTime="15" DelayTime="0" Shared_PosName="eventpos" Shared_PosmValue="0:0:0" BornType="1" Pos1="65.9:9:69.2" Pos2="65.9:9:69.2" Pos3="65.9:9:69.2" Pos4="65.9:9:69.2" FinalPos="65.9:9:69.2" ForcePlace="0" DeltaArg="0" HPPercent="0" />
            <CallMonster Shared_DistName="" Shared_DistmValue="0" Shared_AngleName="" Shared_AnglemValue="135" MonsterId="43258" Shared_MonsterId2Name="" Shared_MonsterId2mValue="0" CopyMonsterId="0" MaxMonsterNum="4" LifeTime="15" DelayTime="0" Shared_PosName="eventpos" Shared_PosmValue="0:0:0" BornType="1" Pos1="65.9:9:69.2" Pos2="65.9:9:69.2" Pos3="65.9:9:69.2" Pos4="65.9:9:69.2" FinalPos="65.9:9:69.2" ForcePlace="0" DeltaArg="0" HPPercent="0" />
            <CallMonster Shared_DistName="" Shared_DistmValue="0" Shared_AngleName="" Shared_AnglemValue="270" MonsterId="43257" Shared_MonsterId2Name="" Shared_MonsterId2mValue="0" CopyMonsterId="0" MaxMonsterNum="4" LifeTime="15" DelayTime="0" Shared_PosName="eventpos" Shared_PosmValue="0:0:0" BornType="1" Pos1="65.9:9:69.2" Pos2="65.9:9:69.2" Pos3="65.9:9:69.2" Pos4="65.9:9:69.2" FinalPos="65.9:9:69.2" ForcePlace="0" DeltaArg="0" HPPercent="0" />
            <CallMonster Shared_DistName="" Shared_DistmValue="0" Shared_AngleName="" Shared_AnglemValue="0" MonsterId="43259" Shared_MonsterId2Name="" Shared_MonsterId2mValue="0" CopyMonsterId="0" MaxMonsterNum="4" LifeTime="15" DelayTime="0" Shared_PosName="eventpos" Shared_PosmValue="0:0:0" BornType="1" Pos1="65.9:9:69.2" Pos2="65.9:9:69.2" Pos3="65.9:9:69.2" Pos4="65.9:9:69.2" FinalPos="65.9:9:69.2" ForcePlace="0" DeltaArg="0" HPPercent="0" />
            <CallMonster Shared_DistName="" Shared_DistmValue="0" Shared_AngleName="" Shared_AnglemValue="225" MonsterId="43258" Shared_MonsterId2Name="" Shared_MonsterId2mValue="0" CopyMonsterId="0" MaxMonsterNum="4" LifeTime="15" DelayTime="0" Shared_PosName="eventpos" Shared_PosmValue="0:0:0" BornType="1" Pos1="65.9:9:69.2" Pos2="65.9:9:69.2" Pos3="65.9:9:69.2" Pos4="65.9:9:69.2" FinalPos="65.9:9:69.2" ForcePlace="0" DeltaArg="0" HPPercent="0" />
            <CallMonster Shared_DistName="" Shared_DistmValue="0" Shared_AngleName="" Shared_AnglemValue="90" MonsterId="43259" Shared_MonsterId2Name="" Shared_MonsterId2mValue="0" CopyMonsterId="0" MaxMonsterNum="4" LifeTime="15" DelayTime="0" Shared_PosName="eventpos" Shared_PosmValue="0:0:0" BornType="1" Pos1="65.9:9:69.2" Pos2="65.9:9:69.2" Pos3="65.9:9:69.2" Pos4="65.9:9:69.2" FinalPos="65.9:9:69.2" ForcePlace="0" DeltaArg="0" HPPercent="0" />
            <CallMonster Shared_DistName="" Shared_DistmValue="0" Shared_AngleName="" Shared_AnglemValue="315" MonsterId="43258" Shared_MonsterId2Name="" Shared_MonsterId2mValue="0" CopyMonsterId="0" MaxMonsterNum="4" LifeTime="15" DelayTime="0" Shared_PosName="eventpos" Shared_PosmValue="0:0:0" BornType="1" Pos1="65.9:9:69.2" Pos2="65.9:9:69.2" Pos3="65.9:9:69.2" Pos4="65.9:9:69.2" FinalPos="65.9:9:69.2" ForcePlace="0" DeltaArg="0" HPPercent="0" />
            <CallMonster Shared_DistName="" Shared_DistmValue="0" Shared_AngleName="" Shared_AnglemValue="45" MonsterId="43260" Shared_MonsterId2Name="" Shared_MonsterId2mValue="0" CopyMonsterId="0" MaxMonsterNum="4" LifeTime="15" DelayTime="0" Shared_PosName="eventpos" Shared_PosmValue="0:0:0" BornType="1" Pos1="65.9:9:69.2" Pos2="65.9:9:69.2" Pos3="65.9:9:69.2" Pos4="65.9:9:69.2" FinalPos="65.9:9:69.2" ForcePlace="0" DeltaArg="0" HPPercent="0" />
            <CallMonster Shared_DistName="" Shared_DistmValue="0" Shared_AngleName="" Shared_AnglemValue="180" MonsterId="43259" Shared_MonsterId2Name="" Shared_MonsterId2mValue="0" CopyMonsterId="0" MaxMonsterNum="4" LifeTime="15" DelayTime="0" Shared_PosName="eventpos" Shared_PosmValue="0:0:0" BornType="1" Pos1="65.9:9:69.2" Pos2="65.9:9:69.2" Pos3="65.9:9:69.2" Pos4="65.9:9:69.2" FinalPos="65.9:9:69.2" ForcePlace="0" DeltaArg="0" HPPercent="0" />
            <CallMonster Shared_DistName="" Shared_DistmValue="0" Shared_AngleName="" Shared_AnglemValue="135" MonsterId="43260" Shared_MonsterId2Name="" Shared_MonsterId2mValue="0" CopyMonsterId="0" MaxMonsterNum="4" LifeTime="15" DelayTime="0" Shared_PosName="eventpos" Shared_PosmValue="0:0:0" BornType="1" Pos1="65.9:9:69.2" Pos2="65.9:9:69.2" Pos3="65.9:9:69.2" Pos4="65.9:9:69.2" FinalPos="65.9:9:69.2" ForcePlace="0" DeltaArg="0" HPPercent="0" />
            <CallMonster Shared_DistName="" Shared_DistmValue="0" Shared_AngleName="" Shared_AnglemValue="270" MonsterId="43259" Shared_MonsterId2Name="" Shared_MonsterId2mValue="0" CopyMonsterId="0" MaxMonsterNum="4" LifeTime="15" DelayTime="0" Shared_PosName="eventpos" Shared_PosmValue="0:0:0" BornType="1" Pos1="65.9:9:69.2" Pos2="65.9:9:69.2" Pos3="65.9:9:69.2" Pos4="65.9:9:69.2" FinalPos="65.9:9:69.2" ForcePlace="0" DeltaArg="0" HPPercent="0" />
            <CallMonster Shared_DistName="" Shared_DistmValue="0" Shared_AngleName="" Shared_AnglemValue="225" MonsterId="43260" Shared_MonsterId2Name="" Shared_MonsterId2mValue="0" CopyMonsterId="0" MaxMonsterNum="4" LifeTime="15" DelayTime="0" Shared_PosName="eventpos" Shared_PosmValue="0:0:0" BornType="1" Pos1="65.9:9:69.2" Pos2="65.9:9:69.2" Pos3="65.9:9:69.2" Pos4="65.9:9:69.2" FinalPos="65.9:9:69.2" ForcePlace="0" DeltaArg="0" HPPercent="0" />
            <CallMonster Shared_DistName="" Shared_DistmValue="0" Shared_AngleName="" Shared_AnglemValue="315" MonsterId="43260" Shared_MonsterId2Name="" Shared_MonsterId2mValue="0" CopyMonsterId="0" MaxMonsterNum="4" LifeTime="15" DelayTime="0" Shared_PosName="eventpos" Shared_PosmValue="0:0:0" BornType="1" Pos1="65.9:9:69.2" Pos2="65.9:9:69.2" Pos3="65.9:9:69.2" Pos4="65.9:9:69.2" FinalPos="65.9:9:69.2" ForcePlace="0" DeltaArg="0" HPPercent="0" />
          </Sequence>
        </Selector>
        <CallScript FuncName="noticedownbreath" DelayTime="0" />
        <AddBuff Shared_MonsterIdName="" Shared_MonsterIdmValue="0" Shared_BuffIdName="" Shared_BuffIdmValue="121441" Shared_BuffId2Name="" Shared_BuffId2mValue="0" Shared_AddBuffTargetName="" Shared_AddBuffTargetmValue="1" Shared_AddBuffWayName="" Shared_AddBuffWaymValue="0" Shared_PlayerProfIdName="" Shared_PlayerProfIdmValue="0" />
      </Sequence>
      <Sequence>
        <ReceiveAIEvent Deprecate="0" MsgType="1" Shared_MsgStrName="eventcmd" Shared_TypeIdName="typeid" Shared_TypeIdmValue="0" Shared_PosName="eventpos" Shared_PosmValue="0:0:0" Shared_SkillTemplateIdName="" Shared_SkillTemplateIdmValue="0" Shared_SkillIdName="eventskillid" Shared_SkillIdmValue="0" Shared_FloatArgName="" Shared_FloatArgmValue="0" Shared_SenderUIDName="" />
        <CompareTo Shared_FirstStringName="eventcmd" Shared_SecondStringName="" secondString="skillhurt" Shared_ResultName="compres" />
        <IntComparison type="2" Shared_Int1Name="compres" int1Value="0" Shared_Int2Name="" int2Value="0" />
        <XHashFunc Input="Monster_desertdragon_helpme_desertdragon" Shared_ResultName="HashRes" Shared_ResultmValue="0" />
        <IntComparison type="2" Shared_Int1Name="eventskillid" int1Value="0" Shared_Int2Name="HashRes" int2Value="0" />
        <CallMonster Shared_DistName="" Shared_DistmValue="0" Shared_AngleName="" Shared_AnglemValue="0" MonsterId="43274" Shared_MonsterId2Name="" Shared_MonsterId2mValue="0" CopyMonsterId="0" MaxMonsterNum="0" LifeTime="6" DelayTime="0" Shared_PosName="eventpos" Shared_PosmValue="0:0:0" BornType="0" Pos1="0:0:0" Pos2="0:0:0" Pos3="0:0:0" Pos4="0:0:0" FinalPos="0:0:0" ForcePlace="0" DeltaArg="0" HPPercent="0" />
      </Sequence>
    </Selector>
  </EntryTask>
</Scene_Memory_DesertDragon_Level6>